{
  "m_GameObject": {
    "m_FileID": 0,
    "m_PathID": 0
  },
  "m_Enabled": 1,
  "m_Script": {
    "m_FileID": 0,
    "m_PathID": -200192584946661878
  },
  "m_Name": "110392013",
  "filename": "110392013",
  "functions": [
    {
      "name": "",
      "args": [],
      "defaultValues": [],
      "commandList": [
        {
          "row": 7,
          "command": "OL_CENTER",
          "args": [],
          "end": 1
        },
        {
          "row": 7,
          "command": "outline",
          "args": [
            "Skip this scene?"
          ],
          "end": 1
        },
        {
          "row": 12,
          "command": "BLACK_OUT_DEF_STOP",
          "args": [],
          "end": 1
        },
        {
          "row": 13,
          "command": "set_BG",
          "args": [
            "0"
          ],
          "end": 1
        },
        {
          "row": 14,
          "command": "window_type",
          "args": [
            "NORMAL"
          ],
          "end": 1
        },
        {
          "row": 15,
          "command": "play_sound",
          "args": [
            "BGM_IN_STORY_0003_05"
          ],
          "end": 1
        },
        {
          "row": 16,
          "command": "show_prologue_book",
          "args": [
            "true",
            "true"
          ],
          "end": 1
        },
        {
          "row": 17,
          "command": "wait",
          "args": [
            "0.1"
          ],
          "end": 1
        },
        {
          "row": 24,
          "command": "add_book_text",
          "args": [
            "Day 13, month of the Prismawyrm.\\n\\nElisanne was kind enough to lend me a book.\\nIt's a little...beyond me, though.",
            "sty_3d_0001_00"
          ],
          "end": 1
        },
        {
          "row": 25,
          "command": "add_book_text",
          "args": [
            "It's a story of a knight and a princess falling\\nin love, but the concept kind of goes over my\\nhead.",
            "sty_3d_0001_00"
          ],
          "end": 1
        },
        {
          "row": 26,
          "command": "add_book_text",
          "args": [
            "Will the day ever come when I think of\\nsomeone as being special to me in that way?",
            "sty_3d_0001_00"
          ],
          "end": 1
        },
        {
          "row": 28,
          "command": "BLACK_IN_DEF",
          "args": [],
          "end": 1
        },
        {
          "row": 29,
          "command": "next_page",
          "args": [
            "0"
          ],
          "end": 1
        },
        {
          "row": 30,
          "command": "next_page",
          "args": [
            "0"
          ],
          "end": 1
        },
        {
          "row": 31,
          "command": "touch_wait",
          "args": [
            "6.0"
          ],
          "end": 1
        },
        {
          "row": 33,
          "command": "wait",
          "args": [
            "0.1"
          ],
          "end": 1
        },
        {
          "row": 35,
          "command": "touch_enable",
          "args": [
            "false"
          ],
          "end": 1
        },
        {
          "row": 36,
          "command": "WFOUT_SHORT",
          "args": [],
          "end": 1
        },
        {
          "row": 37,
          "command": "SEFOUT_DEF",
          "args": [],
          "end": 1
        },
        {
          "row": 39,
          "command": "BLACK_OUT_DEF",
          "args": [],
          "end": 1
        },
        {
          "row": 40,
          "command": "touch_enable",
          "args": [
            "true"
          ],
          "end": 1
        },
        {
          "row": 42,
          "command": "show_prologue_book",
          "args": [
            "false"
          ],
          "end": 1
        },
        {
          "row": 43,
          "command": "set_BG",
          "args": [
            "sty_bg_0027_100"
          ],
          "end": 1
        },
        {
          "row": 44,
          "command": "wait",
          "args": [
            "0.5"
          ],
          "end": 1
        },
        {
          "row": 45,
          "command": "BLACK_IN_DEF",
          "args": [],
          "end": 1
        },
        {
          "row": 51,
          "command": "window_fadein",
          "args": [
            "0",
            "true"
          ],
          "end": 1
        },
        {
          "row": 52,
          "command": "play_sound",
          "args": [
            "VO_CHR_110337_STORY_0042"
          ],
          "end": 1
        },
        {
          "row": 53,
          "command": "print",
          "args": [
            "???",
            "Mm? Is that a diary you're keeping, dear?"
          ],
          "end": 1
        },
        {
          "row": 55,
          "command": "CHARA_SET",
          "args": [
            "M",
            "M",
            "C",
            "c3592",
            "7"
          ],
          "end": 1
        },
        {
          "row": 56,
          "command": "play_sound",
          "args": [
            "VO_CHR_110392_STORY_0011"
          ],
          "end": 1
        },
        {
          "row": 57,
          "command": "print",
          "args": [
            "Nino",
            "Huh? Er, yes, um...?"
          ],
          "end": 1
        },
        {
          "row": 58,
          "command": "CHARA_FADEOUT_DEF",
          "args": [
            "c3592"
          ],
          "end": 1
        },
        {
          "row": 59,
          "command": "WFOUT_DEF",
          "args": [],
          "end": 1
        },
        {
          "row": 61,
          "command": "CHARA_KAMITE_SE",
          "args": [
            "M",
            "M",
            "C",
            "c37372",
            "1",
            "SE_WALK_IN_GR"
          ],
          "end": 1
        },
        {
          "row": 62,
          "command": "play_sound",
          "args": [
            "VO_CHR_110337_STORY_0080"
          ],
          "end": 1
        },
        {
          "row": 63,
          "command": "print",
          "args": [
            "Cassandra",
            "Cassandra. Court sorceress.\\nI keep one too, which is why I ask."
          ],
          "end": 1
        },
        {
          "row": 64,
          "command": "CHARA_FADEOUT_DEF",
          "args": [
            "c37372"
          ],
          "end": 1
        },
        {
          "row": 66,
          "command": "CHARA_SET",
          "args": [
            "M",
            "M",
            "C",
            "c3592",
            "1"
          ],
          "end": 1
        },
        {
          "row": 67,
          "command": "c_bound_b",
          "args": [
            "c3592"
          ],
          "end": 1
        },
        {
          "row": 68,
          "command": "play_sound",
          "args": [
            "VO_CHR_110392_STORY_0080"
          ],
          "end": 1
        },
        {
          "row": 69,
          "command": "print",
          "args": [
            "Nino",
            "I'm Nino."
          ],
          "end": 1
        },
        {
          "row": 70,
          "command": "print",
          "args": [
            "Nino",
            "Nothing beats the feel of watching letters\\nfill up a page from end to end, don't you\\nthink?"
          ],
          "end": 1
        },
        {
          "row": 71,
          "command": "CHARA_FADEOUT_DEF",
          "args": [
            "c3592"
          ],
          "end": 1
        },
        {
          "row": 73,
          "command": "CHARA_SET",
          "args": [
            "M",
            "M",
            "C",
            "c37372",
            "7"
          ],
          "end": 1
        },
        {
          "row": 74,
          "command": "HATENA_EMO",
          "args": [
            "c37372"
          ],
          "end": 1
        },
        {
          "row": 75,
          "command": "play_sound",
          "args": [
            "VO_CHR_110337_STORY_0042"
          ],
          "end": 1
        },
        {
          "row": 76,
          "command": "print",
          "args": [
            "Cassandra",
            "Interesting phrasing. Is that why you keep\\na diary, child? Because you enjoy the act\\nof writing?"
          ],
          "end": 1
        },
        {
          "row": 77,
          "command": "CHARA_FADEOUT_DEF",
          "args": [
            "c37372"
          ],
          "end": 1
        },
        {
          "row": 79,
          "command": "CHARA_SET",
          "args": [
            "M",
            "M",
            "C",
            "c3592",
            "1"
          ],
          "end": 1
        },
        {
          "row": 80,
          "command": "c_bound_b",
          "args": [
            "c3592"
          ],
          "end": 1
        },
        {
          "row": 81,
          "command": "play_sound",
          "args": [
            "VO_CHR_110392_STORY_0030"
          ],
          "end": 1
        },
        {
          "row": 82,
          "command": "print",
          "args": [
            "Nino",
            "Er...yes? Is that strange?"
          ],
          "end": 1
        },
        {
          "row": 83,
          "command": "CHARA_FADEOUT_DEF",
          "args": [
            "c3592"
          ],
          "end": 1
        },
        {
          "row": 85,
          "command": "CHARA_SET",
          "args": [
            "M",
            "M",
            "C",
            "c37372",
            "4"
          ],
          "end": 1
        },
        {
          "row": 86,
          "command": "play_sound",
          "args": [
            "VO_CHR_110337_STORY_0036"
          ],
          "end": 1
        },
        {
          "row": 87,
          "command": "print",
          "args": [
            "Cassandra",
            "I would think most people do it to keep\\na record of their thoughts for posterity."
          ],
          "end": 1
        },
        {
          "row": 88,
          "command": "c_face",
          "args": [
            "M",
            "M",
            "c37372",
            "1"
          ],
          "end": 1
        },
        {
          "row": 89,
          "command": "c_bound_b",
          "args": [
            "c37372"
          ],
          "end": 1
        },
        {
          "row": 90,
          "command": "print",
          "args": [
            "Cassandra",
            "That's my reason, at least."
          ],
          "end": 1
        },
        {
          "row": 91,
          "command": "CHARA_FADEOUT_DEF",
          "args": [
            "c37372"
          ],
          "end": 1
        },
        {
          "row": 93,
          "command": "CHARA_SET",
          "args": [
            "M",
            "M",
            "C",
            "c3592",
            "1"
          ],
          "end": 1
        },
        {
          "row": 94,
          "command": "play_sound",
          "args": [
            "VO_CHR_110392_STORY_0018"
          ],
          "end": 1
        },
        {
          "row": 95,
          "command": "print",
          "args": [
            "Nino",
            "I see. I've just always loved reading and\\nwriting since I was a child."
          ],
          "end": 1
        },
        {
          "row": 96,
          "command": "StopLip_close",
          "args": [
            "c3592"
          ],
          "end": 1
        },
        {
          "row": 97,
          "command": "print",
          "args": [
            "Nino",
            "(I never had any playmates back at the\\nhidden village. Books were about all I\\nhad to pass the time.)"
          ],
          "end": 1
        },
        {
          "row": 98,
          "command": "RestartLip",
          "args": [
            "c3592"
          ],
          "end": 1
        },
        {
          "row": 99,
          "command": "print",
          "args": [
            "Nino",
            "That was what got me started on\\njournaling. I guess I assumed it\\nwas the same for everyone."
          ],
          "end": 1
        },
        {
          "row": 100,
          "command": "print",
          "args": [
            "Nino",
            "Actually, there was even a time when I\\nwanted to be an author when I grew up."
          ],
          "end": 1
        },
        {
          "row": 101,
          "command": "CHARA_FADEOUT_DEF",
          "args": [
            "c3592"
          ],
          "end": 1
        },
        {
          "row": 103,
          "command": "CHARA_SET",
          "args": [
            "M",
            "M",
            "C",
            "c37372",
            "1"
          ],
          "end": 1
        },
        {
          "row": 104,
          "command": "play_sound",
          "args": [
            "VO_CHR_110337_STORY_0084"
          ],
          "end": 1
        },
        {
          "row": 105,
          "command": "print",
          "args": [
            "Cassandra",
            "You've plenty of growing up left to do, my\\ndear. No reason to give up the dream now."
          ],
          "end": 1
        },
        {
          "row": 106,
          "command": "CHARA_FADEOUT_DEF",
          "args": [
            "c37372"
          ],
          "end": 1
        },
        {
          "row": 108,
          "command": "CHARA_SET",
          "args": [
            "M",
            "M",
            "C",
            "c3592",
            "1"
          ],
          "end": 1
        },
        {
          "row": 109,
          "command": "play_sound",
          "args": [
            "VO_CHR_110392_STORY_0011"
          ],
          "end": 1
        },
        {
          "row": 110,
          "command": "print",
          "args": [
            "Nino",
            "You know what? You might be right."
          ],
          "end": 1
        },
        {
          "row": 111,
          "command": "print",
          "args": [
            "Nino",
            "Before, I knew basically nothing about\\nnormal life. Never had a conversation with\\na friend, or a family dinner. I'd never been\\nshopping."
          ],
          "end": 1
        },
        {
          "row": 112,
          "command": "c_face",
          "args": [
            "M",
            "M",
            "c3592",
            "9"
          ],
          "end": 1
        },
        {
          "row": 113,
          "command": "play_sound",
          "args": [
            "VO_CHR_110392_STORY_0024"
          ],
          "end": 1
        },
        {
          "row": 114,
          "command": "print",
          "args": [
            "Nino",
            "All the things I wrote about—all my wildly\\nimaginative fantasies—turned out to be\\ncompletely ordinary."
          ],
          "end": 1
        },
        {
          "row": 115,
          "command": "CHARA_FADEOUT_DEF",
          "args": [
            "c3592"
          ],
          "end": 1
        },
        {
          "row": 117,
          "command": "CHARA_SET",
          "args": [
            "M",
            "M",
            "C",
            "c37372",
            "4"
          ],
          "end": 1
        },
        {
          "row": 118,
          "command": "play_sound",
          "args": [
            "VO_CHR_110337_STORY_0008"
          ],
          "end": 1
        },
        {
          "row": 119,
          "command": "print",
          "args": [
            "Cassandra",
            "Seems you had quite the upbringing."
          ],
          "end": 1
        },
        {
          "row": 120,
          "command": "CHARA_FADEOUT_DEF",
          "args": [
            "c37372"
          ],
          "end": 1
        },
        {
          "row": 122,
          "command": "if",
          "args": [
            "ja_jp"
          ],
          "end": 1
        },
        {
          "row": 123,
          "command": "CHARA_SET",
          "args": [
            "M",
            "M",
            "C",
            "c3592",
            "1"
          ],
          "end": 1
        },
        {
          "row": 124,
          "command": "else",
          "args": [],
          "end": 1
        },
        {
          "row": 125,
          "command": "CHARA_SET",
          "args": [
            "M",
            "M",
            "C",
            "c3592",
            "5"
          ],
          "end": 1
        },
        {
          "row": 126,
          "command": "endif",
          "args": [],
          "end": 1
        },
        {
          "row": 127,
          "command": "c_bound_b",
          "args": [
            "c3592"
          ],
          "end": 1
        },
        {
          "row": 128,
          "command": "play_sound",
          "args": [
            "VO_CHR_110392_STORY_0011"
          ],
          "end": 1
        },
        {
          "row": 129,
          "command": "print",
          "args": [
            "Nino",
            "It was...unique. And yet, the people here\\nhave welcomed me into their home."
          ],
          "end": 1
        },
        {
          "row": 130,
          "command": "c_face",
          "args": [
            "M",
            "M",
            "c3592",
            "5"
          ],
          "end": 1
        },
        {
          "row": 131,
          "command": "print",
          "args": [
            "Nino",
            "Now I'm living the normal life I'd dreamed\\nof for so long. I've never been so happy.\\nI really can't thank you all enough."
          ],
          "end": 1
        },
        {
          "row": 132,
          "command": "CHARA_FADEOUT_DEF",
          "args": [
            "c3592"
          ],
          "end": 1
        },
        {
          "row": 134,
          "command": "CHARA_SET",
          "args": [
            "M",
            "M",
            "C",
            "c37372",
            "1"
          ],
          "end": 1
        },
        {
          "row": 135,
          "command": "play_sound",
          "args": [
            "VO_CHR_110337_STORY_0079"
          ],
          "end": 1
        },
        {
          "row": 136,
          "command": "print",
          "args": [
            "Cassandra",
            "So even the humdrum routines of everyday\\nlife can feel like storybook reveries to the\\nright person. Fascinating."
          ],
          "end": 1
        },
        {
          "row": 137,
          "command": "print",
          "args": [
            "Cassandra",
            "That record you're keeping may just\\nbecome a document of vast historical\\nimportance in the future."
          ],
          "end": 1
        },
        {
          "row": 138,
          "command": "CHARA_FADEOUT_DEF",
          "args": [
            "c37372"
          ],
          "end": 1
        },
        {
          "row": 140,
          "command": "CHARA_SET",
          "args": [
            "M",
            "M",
            "C",
            "c3592",
            "7"
          ],
          "end": 1
        },
        {
          "row": 141,
          "command": "HATENA_EMO",
          "args": [
            "c3592"
          ],
          "end": 1
        },
        {
          "row": 142,
          "command": "play_sound",
          "args": [
            "VO_CHR_110392_STORY_0042"
          ],
          "end": 1
        },
        {
          "row": 143,
          "command": "print",
          "args": [
            "Nino",
            "Why do you say that?"
          ],
          "end": 1
        },
        {
          "row": 144,
          "command": "CHARA_FADEOUT_DEF",
          "args": [
            "c3592"
          ],
          "end": 1
        },
        {
          "row": 146,
          "command": "CHARA_SET",
          "args": [
            "M",
            "M",
            "C",
            "c37372",
            "1"
          ],
          "end": 1
        },
        {
          "row": 147,
          "command": "play_sound",
          "args": [
            "VO_CHR_110337_STORY_0030"
          ],
          "end": 1
        },
        {
          "row": 148,
          "command": "print",
          "args": [
            "Cassandra",
            "Well, considering what it is our little\\nprince and the others are trying to\\naccomplish here..."
          ],
          "end": 1
        },
        {
          "row": 149,
          "command": "print",
          "args": [
            "Cassandra",
            "A chronicle of the path they traced\\nmay hold profound meaning someday."
          ],
          "end": 1
        },
        {
          "row": 150,
          "command": "CHARA_FADEOUT_DEF",
          "args": [
            "c37372"
          ],
          "end": 1
        },
        {
          "row": 152,
          "command": "CHARA_SET",
          "args": [
            "M",
            "M",
            "C",
            "c3592",
            "7"
          ],
          "end": 1
        },
        {
          "row": 153,
          "command": "print",
          "args": [
            "Nino",
            "Wow. That kind of boggles the mind."
          ],
          "end": 1
        },
        {
          "row": 154,
          "command": "WFOUT_DEF",
          "args": [],
          "end": 1
        },
        {
          "row": 155,
          "command": "play_sound",
          "args": [
            "SE_STORY_COMMON_0186"
          ],
          "end": 1
        },
        {
          "row": 156,
          "command": "set_volume",
          "args": [
            "0",
            "0.0",
            "SE_STORY_COMMON_0186"
          ],
          "end": 1
        },
        {
          "row": 157,
          "command": "set_volume",
          "args": [
            "1",
            "0.5",
            "SE_STORY_COMMON_0186"
          ],
          "end": 1
        },
        {
          "row": 159,
          "command": "wait",
          "args": [
            "3.0"
          ],
          "end": 1
        },
        {
          "row": 160,
          "command": "stop_se",
          "args": [
            "2.0"
          ],
          "end": 1
        },
        {
          "row": 161,
          "command": "BLACK_OUT_LONG",
          "args": [],
          "end": 1
        },
        {
          "row": 162,
          "command": "BGMFOUT_DEF",
          "args": [],
          "end": 1
        },
        {
          "row": 163,
          "command": "wait",
          "args": [
            "1.0"
          ],
          "end": 1
        },
        {
          "row": 164,
          "command": "CHARA_FADEOUT_DEF",
          "args": [
            "c3592"
          ],
          "end": 1
        },
        {
          "row": 165,
          "command": "set_BG",
          "args": [
            "0"
          ],
          "end": 1
        },
        {
          "row": 173,
          "command": "play_sound",
          "args": [
            "BGM_IN_STORY_0006_01"
          ],
          "end": 1
        },
        {
          "row": 174,
          "command": "show_prologue_book",
          "args": [
            "true",
            "true"
          ],
          "end": 1
        },
        {
          "row": 175,
          "command": "wait",
          "args": [
            "0.1"
          ],
          "end": 1
        },
        {
          "row": 177,
          "command": "add_book_text",
          "args": [
            "Day 14, month of the Prismawyrm.\\n\\nI spoke about diaries with a woman named\\nCassandra.",
            "sty_3d_0001_00"
          ],
          "end": 1
        },
        {
          "row": 178,
          "command": "add_book_text",
          "args": [
            "I had never even considered that someone\\nelse might read these entries.",
            "sty_3d_0001_00"
          ],
          "end": 1
        },
        {
          "row": 179,
          "command": "add_book_text",
          "args": [
            "Could these idle thoughts and ramblings really\\nhold any meaning for anyone besides myself?",
            "sty_3d_0001_00"
          ],
          "end": 1
        },
        {
          "row": 181,
          "command": "BLACK_IN_DEF",
          "args": [],
          "end": 1
        },
        {
          "row": 182,
          "command": "next_page",
          "args": [
            "0"
          ],
          "end": 1
        },
        {
          "row": 183,
          "command": "next_page",
          "args": [
            "0"
          ],
          "end": 1
        },
        {
          "row": 184,
          "command": "touch_wait",
          "args": [
            "6.0"
          ],
          "end": 1
        },
        {
          "row": 186,
          "command": "wait",
          "args": [
            "0.1"
          ],
          "end": 1
        },
        {
          "row": 188,
          "command": "touch_enable",
          "args": [
            "false"
          ],
          "end": 1
        },
        {
          "row": 189,
          "command": "WFOUT_SHORT",
          "args": [],
          "end": 1
        },
        {
          "row": 190,
          "command": "SEFOUT_DEF",
          "args": [],
          "end": 1
        },
        {
          "row": 192,
          "command": "BLACK_OUT_DEF",
          "args": [],
          "end": 1
        },
        {
          "row": 193,
          "command": "touch_enable",
          "args": [
            "true"
          ],
          "end": 1
        },
        {
          "row": 195,
          "command": "show_prologue_book",
          "args": [
            "false"
          ],
          "end": 1
        },
        {
          "row": 196,
          "command": "set_BG",
          "args": [
            "sty_bg_0027_100"
          ],
          "end": 1
        },
        {
          "row": 197,
          "command": "wait",
          "args": [
            "0.5"
          ],
          "end": 1
        },
        {
          "row": 198,
          "command": "CHARA_SET",
          "args": [
            "M",
            "Q",
            "C",
            "c3592",
            "1"
          ],
          "end": 1
        },
        {
          "row": 199,
          "command": "BLACK_IN_DEF",
          "args": [],
          "end": 1
        },
        {
          "row": 203,
          "command": "print",
          "args": [
            "Nino",
            "(Something written without any deep\\nthought that would later influence\\nothers...)"
          ],
          "end": 1
        },
        {
          "row": 204,
          "command": "RestartLip",
          "args": [
            "c3592"
          ],
          "end": 1
        },
        {
          "row": 205,
          "command": "print",
          "args": [
            "Nino",
            "I'm sure the Scrolls of Perdition are a\\nprime example of that."
          ],
          "end": 1
        },
        {
          "row": 206,
          "command": "StopLip_close",
          "args": [
            "c3592"
          ],
          "end": 1
        },
        {
          "row": 207,
          "command": "print",
          "args": [
            "Nino",
            "(My ancestor documented history as it truly\\nhappened, and entrusted the key to her\\nfamily line.)"
          ],
          "end": 1
        },
        {
          "row": 208,
          "command": "c_swing_h_slow",
          "args": [
            "c3592"
          ],
          "end": 1
        },
        {
          "row": 209,
          "command": "print",
          "args": [
            "Nino",
            "(Why she bothered to leave behind such\\na nuisance has always escaped me.)"
          ],
          "end": 1
        },
        {
          "row": 210,
          "command": "print",
          "args": [
            "Nino",
            "(It's not as if she wanted to pass that truth\\non to anyone. Maybe she just wanted to\\nknow that it existed, in some form.)"
          ],
          "end": 1
        },
        {
          "row": 211,
          "command": "RestartLip",
          "args": [
            "c3592"
          ],
          "end": 1
        },
        {
          "row": 212,
          "command": "print",
          "args": [
            "Nino",
            "The truth, lost from living memory...\\nHer daughter's existence..."
          ],
          "end": 1
        },
        {
          "row": 213,
          "command": "StopLip_close",
          "args": [
            "c3592"
          ],
          "end": 1
        },
        {
          "row": 214,
          "command": "print",
          "args": [
            "Nino",
            "(Maybe she meant it to be a record for\\nherself alone—to keep her own memories\\nalive.)"
          ],
          "end": 1
        },
        {
          "row": 215,
          "command": "c_face",
          "args": [
            "M",
            "M",
            "c3592",
            "9"
          ],
          "end": 1
        },
        {
          "row": 216,
          "command": "play_sound",
          "args": [
            "VO_CHR_110392_STORY_0024"
          ],
          "end": 1
        },
        {
          "row": 217,
          "command": "print",
          "args": [
            "Nino",
            "That's so sad..."
          ],
          "end": 1
        },
        {
          "row": 219,
          "command": "BLACK_OUT_DEF",
          "args": [],
          "end": 1
        },
        {
          "row": 220,
          "command": "CHARA_FADEOUT_DEF",
          "args": [
            "c3592"
          ],
          "end": 1
        },
        {
          "row": 221,
          "command": "set_BG",
          "args": [
            "0"
          ],
          "end": 1
        },
        {
          "row": 225,
          "command": "show_prologue_book",
          "args": [
            "true",
            "true"
          ],
          "end": 1
        },
        {
          "row": 226,
          "command": "wait",
          "args": [
            "0.1"
          ],
          "end": 1
        },
        {
          "row": 228,
          "command": "add_book_text",
          "args": [
            "Today, I felt sympathy for my ancestor for the\\nfirst time in my life.",
            "sty_3d_0001_00"
          ],
          "end": 1
        },
        {
          "row": 229,
          "command": "add_book_text",
          "args": [
            "I'm certain I never would have felt this emotion\\nif I hadn't seen the world outside.",
            "sty_3d_0001_00"
          ],
          "end": 1
        },
        {
          "row": 230,
          "command": "add_book_text",
          "args": [
            "It's all because you set me free, Tobias.\\nWhat I'd give to see you again.",
            "sty_3d_0001_00"
          ],
          "end": 1
        },
        {
          "row": 232,
          "command": "BLACK_IN_DEF",
          "args": [],
          "end": 1
        },
        {
          "row": 233,
          "command": "next_page",
          "args": [
            "0"
          ],
          "end": 1
        },
        {
          "row": 234,
          "command": "next_page",
          "args": [
            "0"
          ],
          "end": 1
        },
        {
          "row": 235,
          "command": "touch_wait",
          "args": [
            "6.0"
          ],
          "end": 1
        },
        {
          "row": 237,
          "command": "wait",
          "args": [
            "0.1"
          ],
          "end": 1
        },
        {
          "row": 239,
          "command": "touch_enable",
          "args": [
            "false"
          ],
          "end": 1
        },
        {
          "row": 240,
          "command": "WFOUT_SHORT",
          "args": [],
          "end": 1
        },
        {
          "row": 241,
          "command": "SEFOUT_DEF",
          "args": [],
          "end": 1
        },
        {
          "row": 243,
          "command": "BLACK_OUT_DEF",
          "args": [],
          "end": 1
        },
        {
          "row": 244,
          "command": "touch_enable",
          "args": [
            "true"
          ],
          "end": 1
        },
        {
          "row": 246,
          "command": "show_prologue_book",
          "args": [
            "false"
          ],
          "end": 1
        },
        {
          "row": 247,
          "command": "BGMFOUT_DEF",
          "args": [],
          "end": 1
        },
        {
          "row": 248,
          "command": "BLACK_IN_DEF",
          "args": [],
          "end": 1
        },
        {
          "row": 254,
          "command": "BLACK_OUT_DEF_STOP",
          "args": [],
          "end": 1
        },
        {
          "row": 255,
          "command": "end",
          "args": [],
          "end": 1
        }
      ],
      "variables": {
        "buckets": [
          -1,
          -1,
          -1
        ],
        "count": 0,
        "entriesHashCode": [
          0,
          0,
          0
        ],
        "entriesNext": [
          0,
          0,
          0
        ],
        "entriesKey": [
          "",
          "",
          ""
        ],
        "entriesValue": [
          "",
          "",
          ""
        ],
        "freeCount": 0,
        "freeList": -1
      }
    }
  ]
}